README
setup.py
pyparallelcurl/pyparallelcurl.py
pyparallelcurl/test.py
pyparallelcurl.egg-info/PKG-INFO
pyparallelcurl.egg-info/SOURCES.txt
pyparallelcurl.egg-info/dependency_links.txt
pyparallelcurl.egg-info/requires.txt
pyparallelcurl.egg-info/top_level.txt