Metadata-Version: 1.0
Name: pyparallelcurl
Version: 0.0.3
Summary: A simple interface for fetching URL resources in parallel without threads
Home-page: http://github.com/petewarden/pyparallelcurl
Author: Pete Warden
Author-email: pete@mailana.com
License: BSD
Keywords: curl parallel
Platform: UNKNOWN
Classifier: Development Status :: 3 - Alpha
Classifier: Topic :: Utilities
Classifier: License :: OSI Approved :: BSD License
